README.md
pyproject.toml
pulumi_oci/__init__.py
pulumi_oci/_utilities.py
pulumi_oci/provider.py
pulumi_oci/pulumi-plugin.json
pulumi_oci/py.typed
pulumi_oci.egg-info/PKG-INFO
pulumi_oci.egg-info/SOURCES.txt
pulumi_oci.egg-info/dependency_links.txt
pulumi_oci.egg-info/requires.txt
pulumi_oci.egg-info/top_level.txt
pulumi_oci/adm/__init__.py
pulumi_oci/adm/_inputs.py
pulumi_oci/adm/get_knowledgebase.py
pulumi_oci/adm/get_knowledgebases.py
pulumi_oci/adm/get_remediation_recipe.py
pulumi_oci/adm/get_remediation_recipes.py
pulumi_oci/adm/get_remediation_run.py
pulumi_oci/adm/get_remediation_run_application_dependency_recommendations.py
pulumi_oci/adm/get_remediation_run_stage.py
pulumi_oci/adm/get_remediation_run_stages.py
pulumi_oci/adm/get_remediation_runs.py
pulumi_oci/adm/get_vulnerability_audit.py
pulumi_oci/adm/get_vulnerability_audit_application_dependency_vulnerabilities.py
pulumi_oci/adm/get_vulnerability_audit_application_dependency_vulnerability.py
pulumi_oci/adm/get_vulnerability_audits.py
pulumi_oci/adm/knowledge_base.py
pulumi_oci/adm/outputs.py
pulumi_oci/adm/remediation_recipe.py
pulumi_oci/adm/remediation_run.py
pulumi_oci/adm/vulnerability_audit.py
pulumi_oci/aianomalydetection/__init__.py
pulumi_oci/aianomalydetection/_inputs.py
pulumi_oci/aianomalydetection/ai_private_endpoint.py
pulumi_oci/aianomalydetection/data_asset.py
pulumi_oci/aianomalydetection/detect_anomaly_job.py
pulumi_oci/aianomalydetection/get_ai_private_endpoint.py
pulumi_oci/aianomalydetection/get_ai_private_endpoints.py
pulumi_oci/aianomalydetection/get_detect_anomaly_job.py
pulumi_oci/aianomalydetection/get_detect_anomaly_jobs.py
pulumi_oci/aianomalydetection/get_detection_data_asset.py
pulumi_oci/aianomalydetection/get_detection_data_assets.py
pulumi_oci/aianomalydetection/get_detection_model.py
pulumi_oci/aianomalydetection/get_detection_models.py
pulumi_oci/aianomalydetection/get_detection_project.py
pulumi_oci/aianomalydetection/get_detection_projects.py
pulumi_oci/aianomalydetection/model.py
pulumi_oci/aianomalydetection/outputs.py
pulumi_oci/aianomalydetection/project.py
pulumi_oci/aidocument/__init__.py
pulumi_oci/aidocument/_inputs.py
